BankDetails/__init__.py
BankDetails/bank.py
BankDetails/bank_day_details.py
BankDetails/bank_test.py
BankDetails/config.py
BankDetails/manage.py
OtherWare/__init__.py
OtherWare/metadata.py
OtherWare/utility.py
crmCustomer/DatabaseOperations.py
crmCustomer/Metadata.py
crmCustomer/Utility.py
crmCustomer/__init__.py
crmCustomer/customerOAInterface.py
crmCustomer/src_crm_customer.py
crmCustomer/test_customer.py
crmMaterial/CRMsaveMaterial.py
crmMaterial/__init__.py
crmMaterial/login.py
crmMaterial/manage.py
crmMaterial/product.py
crmMaterial/src_crm_material.py
crmNoticeShipment/EcsInterface.py
crmNoticeShipment/__init__.py
crmNoticeShipment/mainModel.py
crmNoticeShipment/metadata.py
crmNoticeShipment/operation.py
crmNoticeShipment/src_crm_notice.py
crmNoticeShipment/utility.py
crmSaleBilling/EcsInterface.py
crmSaleBilling/__init__.py
crmSaleBilling/mainModel.py
crmSaleBilling/metadata.py
crmSaleBilling/operation.py
crmSaleBilling/src_crm_salebilling.py
crmSaleBilling/utility.py
crmSaleOrder/EcsInterface.py
crmSaleOrder/__init__.py
crmSaleOrder/mainModel.py
crmSaleOrder/metadata.py
crmSaleOrder/operation.py
crmSaleOrder/src_crm_saleorder.py
crmSaleOrder/utility.py
erp2crmsaleic/__init__.py
erp2crmsaleic/config.py
erp2crmsaleic/saleicSaveCrm.py
erp2crmsaleic/salesicToCRM.py
erp2crmsaleout/__init__.py
erp2crmsaleout/config.py
erp2crmsaleout/manage.py
erp2crmsaleout/saleOutToDMS.py
erp2crmsaleout/salesOutStock.py
erptocrmsaleic/__init__.py
erptocrmsaleic/config.py
erptocrmsaleic/manage.py
erptocrmsaleic/saleicSaveCrm.py
erptocrmsaleic/salesicToCRM.py
log_return/__init__.py
log_return/ret_log.py
query_log/__init__.py
query_log/log.py
rdCustomer/DatabaseOperations.py
rdCustomer/Metadata.py
rdCustomer/Utility.py
rdCustomer/__init__.py
rdCustomer/customerOAInterface.py
rdSaleOrder/EcsInterface.py
rdSaleOrder/__init__.py
rdSaleOrder/mainModel.py
rdSaleOrder/metadata.py
rdSaleOrder/operation.py
rdSaleOrder/utility.py
rdSupplier/DatabaseOperations.py
rdSupplier/Metadata.py
query_log-1.0.4.dist-info/METADATA
query_log-1.0.4.dist-info/WHEEL
query_log-1.0.4.dist-info/top_level.txt
query_log-1.0.4.dist-info/RECORD
