Metadata-Version: 2.1
Name: query-log
Version: 1.0.4
Summary: test for zip
Home-page: UNKNOWN
Author: yb
Author-email: 623374149@qq.com
License: UNKNOWN
Platform: UNKNOWN
